Metadata-Version: 2.1
Name: AutoReg
Version: 1.1
Summary: A lightweight library to get regex of a string.
Home-page: https://github.com/SusmitPanda/AutoReg
Author: SusmitPanda
Author-email: susmit.vssut@gmail.com
License: MIT
Keywords: regex,python regex,autoregex,regex create,string matching
Platform: UNKNOWN
Classifier: Development Status :: 3 - Alpha
Classifier: Intended Audience :: Developers
Classifier: Topic :: Software Development :: Build Tools
Classifier: License :: OSI Approved :: MIT License
Classifier: Programming Language :: Python :: 3
Classifier: Programming Language :: Python :: 3.4
Classifier: Programming Language :: Python :: 3.5
Classifier: Programming Language :: Python :: 3.6
Classifier: Programming Language :: Python :: 3.7
Classifier: Programming Language :: Python :: 3.8
Classifier: Programming Language :: Python :: 3.9
License-File: LICENSE
